{"stats":{"minecraft:dropped":{"minecraft:iron_ingot":8,"minecraft:wheat_seeds":9,"minecraft:feather":3,"minecraft:cobblestone":66,"minecraft:dirt":2,"mekanism:raw_osmium":75,"minecraft:iron_pickaxe":1,"botania:black_double_flower":1,"minecraft:iron_shovel":1,"minecraft:bone":2,"minecraft:stone_axe":2,"mekanism:ingot_osmium":2,"minecraft:iron_nugget":6,"minecraft:raw_iron":33,"minecraft:rotten_flesh":16,"create:asurine":1,"mekanismtools:osmium_chestplate":1,"minecraft:poppy":1,"mysticalagriculture:tertium_sword":1,"minecraft:stone":17,"minecraft:beef":72,"minecraft:wooden_pickaxe":2,"minecraft:arrow":2,"minecraft:stone_pickaxe":1,"mekanismtools:osmium_leggings":1,"mysticalagriculture:inferium_pickaxe":1},"minecraft:killed":{"minecraft:spider":1,"minecraft:skeleton":2,"minecraft:chicken":5,"minecraft:pig":16,"minecraft:creeper":1,"minecraft:sheep":4,"minecraft:zombie":16,"minecraft:cow":16},"minecraft:used":{"botania:red_double_flower":1,"minecraft:iron_shovel":145,"minecraft:acacia_log":4,"minecraft:chest":1,"minecraft:spruce_planks":4,"minecraft:stone_hoe":30,"minecraft:cooked_chicken":3,"minecraft:torch":62,"minecraft:dirt":216,"minecraft:mutton":1,"create:white_sail":3,"mekanismtools:osmium_sword":1,"minecraft:cobblestone_wall":8,"ironchest:iron_chest":1,"minecraft:acacia_sapling":1,"create:depot":3,"minecraft:lava_bucket":10,"minecraft:iron_helmet":13,"minecraft:stone_brick_stairs":18,"minecraft:stone_bricks":22,"minecraft:dark_oak_boat":1,"create:shaft":4,"minecraft:oak_sapling":2,"minecraft:furnace":2,"minecraft:egg":7,"minecraft:cooked_beef":2,"minecraft:cooked_mutton":2,"minecraft:water_bucket":33,"minecraft:diorite":1,"minecraft:stone_pickaxe":235,"minecraft:wooden_pickaxe":44,"mekanismtools:osmium_axe":29,"minecraft:sugar_cane":8,"minecraft:white_wool":1,"create:encased_fan":1,"minecraft:crafting_table":7,"minecraft:white_bed":3,"mekanismtools:osmium_pickaxe":13,"create:mechanical_press":4,"create:windmill_bearing":2,"minecraft:bread":4,"minecraft:iron_pickaxe":95,"create:water_wheel":1,"create:large_water_wheel":4,"minecraft:stone_axe":162,"minecraft:pink_petals":5,"mekanismtools:osmium_shovel":60,"minecraft:cobblestone":24,"minecraft:cooked_porkchop":16,"minecraft:bucket":44,"create:hand_crank":3},"minecraft:custom":{"minecraft:mob_kills":61,"minecraft:interact_with_crafting_table":41,"minecraft:damage_dealt_resisted":0,"minecraft:leave_game":2,"minecraft:time_since_death":5880,"minecraft:climb_one_cm":1295,"minecraft:sprint_one_cm":335909,"minecraft:walk_one_cm":193804,"minecraft:drop":75,"minecraft:play_time":127236,"minecraft:sneak_time":18863,"minecraft:deaths":2,"minecraft:walk_under_water_one_cm":14769,"minecraft:boat_one_cm":91829,"minecraft:jump":2450,"minecraft:walk_on_water_one_cm":21169,"minecraft:total_world_time":127236,"minecraft:interact_with_furnace":17,"minecraft:sleep_in_bed":10,"minecraft:time_since_rest":5905,"minecraft:waystone_activated":1,"minecraft:damage_taken":2054,"minecraft:trigger_trapped_chest":1,"minecraft:damage_dealt":7372,"minecraft:swim_one_cm":37750,"minecraft:fly_one_cm":485166,"minecraft:open_chest":31,"minecraft:crouch_one_cm":58882,"minecraft:fall_one_cm":82354},"minecraft:picked_up":{"minecraft:crafting_table":7,"minecraft:chicken":5,"botania:black_double_flower":1,"minecraft:stone_brick_stairs":10,"mysticalagriculture:tertium_sword":1,"create:water_wheel":1,"mysticalagriculture:inferium_essence":28,"create:mechanical_press":3,"minecraft:cobbled_deepslate":1,"minecraft:spruce_planks":12,"minecraft:beef":74,"minecraft:poppy":1,"minecraft:iron_nugget":6,"minecraft:melon_slice":38,"minecraft:sugar_cane":17,"minecraft:spruce_trapdoor":6,"minecraft:furnace":1,"minecraft:egg":7,"minecraft:raw_iron":75,"apotheosis:gem":7,"minecraft:stone":50,"minecraft:torch":10,"mysticalagriculture:prosperity_shard":8,"minecraft:acacia_log":12,"create:andesite_casing":3,"minecraft:porkchop":31,"create:windmill_bearing":1,"minecraft:cherry_log":23,"create:hand_crank":3,"minecraft:diorite":33,"mekanism:raw_tin":8,"minecraft:arrow":4,"minecraft:rotten_flesh":16,"minecraft:hay_block":29,"create:asurine":1,"create:depot":2,"mekanism:ingot_osmium":27,"minecraft:mutton":4,"minecraft:white_wool":11,"minecraft:cobblestone":126,"minecraft:pink_petals":5,"minecraft:feather":3,"mekanism:raw_lead":1,"minecraft:andesite":15,"minecraft:leather":11,"minecraft:oak_log":5,"minecraft:cobblestone_wall":8,"minecraft:gunpowder":1,"minecraft:lapis_lazuli":17,"minecraft:dirt":218,"mysticalagriculture:inferium_pickaxe":1,"minecraft:bone":2,"minecraft:stone_bricks":26,"minecraft:wheat_seeds":17,"minecraft:iron_ingot":37,"minecraft:cooked_chicken":3,"minecraft:bamboo":19,"minecraft:acacia_sapling":1,"minecraft:book":3,"create:large_water_wheel":3,"mekanismtools:osmium_chestplate":1,"minecraft:white_bed":2,"minecraft:dark_oak_log":6,"mekanism:raw_osmium":75,"botania:red_double_flower":1,"mekanismtools:osmium_leggings":1,"minecraft:diamond":4,"minecraft:stone_axe":1,"minecraft:iron_helmet":1,"minecraft:gray_wool":1,"create:white_sail":3,"minecraft:oak_sapling":2,"minecraft:coal":55},"minecraft:crafted":{"minecraft:cherry_planks":4,"minecraft:oak_planks":20,"minecraft:dark_oak_boat":1,"minecraft:iron_nugget":45,"create:white_sail":12,"minecraft:cherry_slab":6,"mekanismtools:osmium_shovel":1,"mekanismtools:osmium_chestplate":1,"minecraft:furnace":1,"minecraft:cooked_mutton":2,"mekanismtools:osmium_axe":1,"create:mechanical_press":1,"minecraft:stone_pickaxe":2,"minecraft:chest":2,"minecraft:dark_oak_planks":24,"minecraft:stone_hoe":1,"minecraft:stone_bricks":32,"create:windmill_bearing":1,"mekanismtools:osmium_pickaxe":1,"minecraft:cooked_beef":2,"mekanismtools:osmium_sword":1,"create:depot":1,"create:andesite_alloy":17,"create:hand_crank":1,"minecraft:cooked_porkchop":31,"minecraft:crafting_table":2,"minecraft:wooden_pickaxe":2,"create:large_water_wheel":1,"minecraft:bucket":1,"mekanismtools:osmium_leggings":1,"minecraft:stone_axe":2,"minecraft:air":0,"create:encased_fan":1,"minecraft:stone_brick_stairs":8,"create:water_wheel":1,"minecraft:stick":52,"minecraft:iron_ingot":42,"minecraft:iron_pickaxe":1,"minecraft:iron_block":1,"minecraft:iron_shovel":1,"create:propeller":1,"minecraft:white_bed":1,"create:shaft":16,"minecraft:andesite":20,"minecraft:acacia_planks":32,"minecraft:torch":52,"minecraft:shears":1,"ironchest:iron_chest":1},"minecraft:broken":{"minecraft:stone_pickaxe":1,"minecraft:stone_axe":1},"minecraft:mined":{"create:zinc_ore":1,"mysticalagriculture:prosperity_ore":3,"minecraft:diamond_ore":4,"minecraft:spruce_planks":4,"minecraft:white_bed":2,"create:andesite_casing":3,"minecraft:cherry_log":23,"minecraft:dark_oak_log":6,"minecraft:acacia_log":12,"minecraft:grass_block":115,"create:depot":2,"botania:black_double_flower":1,"mysticalagriculture:inferium_ore":3,"minecraft:hay_block":30,"minecraft:furnace":1,"minecraft:iron_ore":73,"create:white_sail":3,"minecraft:andesite":15,"minecraft:deepslate_lapis_ore":2,"create:windmill_bearing":1,"create:asurine":2,"minecraft:deepslate_iron_ore":2,"minecraft:vine":2,"minecraft:bamboo":2,"minecraft:stone":95,"create:mechanical_press":3,"mekanism:osmium_ore":36,"minecraft:crafting_table":6,"minecraft:torch":6,"minecraft:melon":7,"mekanism:tin_ore":8,"create:water_wheel":1,"minecraft:cobblestone":2,"minecraft:sugar_cane":6,"minecraft:diorite":33,"minecraft:wall_torch":2,"create:large_water_wheel":3,"minecraft:pink_petals":3,"botania:red_double_flower":1,"minecraft:grass":104,"botania:gray_mushroom":1,"minecraft:oak_log":5,"minecraft:coal_ore":49,"mekanism:lead_ore":1,"create:hand_crank":1,"minecraft:cherry_leaves":6,"minecraft:dirt":100,"minecraft:stone_bricks":11,"minecraft:oak_leaves":6,"mysticalagriculture:deepslate_inferium_ore":1,"minecraft:deepslate":1,"minecraft:fern":16}},"DataVersion":3465}